__init__.py
exetimer.py
exetimer-0.0.5.dist-info/LICENSE
exetimer-0.0.5.dist-info/METADATA
exetimer-0.0.5.dist-info/WHEEL
exetimer-0.0.5.dist-info/top_level.txt
exetimer-0.0.5.dist-info/RECORD
